LICENSE
MANIFEST.in
README.md
setup.py
ax/pipeline.py
ax/lib/libsample_h264_ivps_joint_vo_sipy.so
ax/lib/libsample_h264_ivps_joint_vo_sipy.so.1
ax/lib/libsample_h264_ivps_joint_vo_sipy.so.1.1.3
ax/lib/libsample_mp4_ivps_joint_vo_sipy.so
ax/lib/libsample_mp4_ivps_joint_vo_sipy.so.1
ax/lib/libsample_mp4_ivps_joint_vo_sipy.so.1.1.3
ax/lib/libsample_multi_rtsp_ivps_joint_multi_rtsp_sipy.so
ax/lib/libsample_multi_rtsp_ivps_joint_multi_rtsp_sipy.so.1
ax/lib/libsample_multi_rtsp_ivps_joint_multi_rtsp_sipy.so.1.1.3
ax/lib/libsample_rtsp_ivps_joint_rtsp_sipy.so
ax/lib/libsample_rtsp_ivps_joint_rtsp_sipy.so.1
ax/lib/libsample_rtsp_ivps_joint_rtsp_sipy.so.1.1.3
ax/lib/libsample_rtsp_ivps_joint_rtsp_vo_sipy.so
ax/lib/libsample_rtsp_ivps_joint_rtsp_vo_sipy.so.1
ax/lib/libsample_rtsp_ivps_joint_rtsp_vo_sipy.so.1.1.3
ax/lib/libsample_rtsp_ivps_joint_vo_sipy.so
ax/lib/libsample_rtsp_ivps_joint_vo_sipy.so.1
ax/lib/libsample_rtsp_ivps_joint_vo_sipy.so.1.1.3
ax/lib/libsample_v4l2_user_ivps_joint_vo_sipy.so
ax/lib/libsample_v4l2_user_ivps_joint_vo_sipy.so.1
ax/lib/libsample_v4l2_user_ivps_joint_vo_sipy.so.1.1.3
ax/lib/libsample_vin_ivps_joint_venc_rtsp_sipy.so
ax/lib/libsample_vin_ivps_joint_venc_rtsp_sipy.so.1
ax/lib/libsample_vin_ivps_joint_venc_rtsp_sipy.so.1.1.3
ax/lib/libsample_vin_ivps_joint_venc_rtsp_vo_sipy.so
ax/lib/libsample_vin_ivps_joint_venc_rtsp_vo_sipy.so.1
ax/lib/libsample_vin_ivps_joint_venc_rtsp_vo_sipy.so.1.1.3
ax/lib/libsample_vin_ivps_joint_vo_h265_sipy.so
ax/lib/libsample_vin_ivps_joint_vo_h265_sipy.so.1
ax/lib/libsample_vin_ivps_joint_vo_h265_sipy.so.1.1.3
ax/lib/libsample_vin_ivps_joint_vo_sipy.so
ax/lib/libsample_vin_ivps_joint_vo_sipy.so.1
ax/lib/libsample_vin_ivps_joint_vo_sipy.so.1.1.3
ax_pipeline_api.egg-info/PKG-INFO
ax_pipeline_api.egg-info/SOURCES.txt
ax_pipeline_api.egg-info/dependency_links.txt
ax_pipeline_api.egg-info/top_level.txt
src/m3axpi.cpp
src/axdl/include/c_api.h
src/common/common_cam.h
src/common/common_func.h
src/common/common_pipeline.h
src/common/common_sys.h
src/common/common_vin.h
src/utilities/sample_log.h
tests/test_ax_pose_print.py
tests/test_m3axpi_module.py
tests/test_yolov5s_pillow.py