Metadata-Version: 2.1
Name: ax-pipeline-api
Version: 1.1.3
Summary: A Python API For wiki.sipeed.com/m3axpi Pipeline
Home-page: https://github.com/junhuanchen/ax-pipeline-api
Author: Juwan
Author-email: junhuanchen@qq.com
License: MIT
Classifier: Programming Language :: Python :: 3
License-File: LICENSE
